optevolver/__init__.py
optevolver/generators/FloatFunctions.py
optevolver/generators/IntFunctions.py
optevolver/generators/JackTorrance.py
optevolver/generators/TextTokenizer.py
optevolver/generators/__init__.py
optevolver/hyperparameter/EnumeratedTypes.py
optevolver/hyperparameter/EvolutionaryOptimizer.py
optevolver/hyperparameter/ModelWriter.py
optevolver/hyperparameter/TF2OptimizationTest.py
optevolver/hyperparameter/TF2OptimizerTestBase.py
optevolver/hyperparameter/ValueAxis.py
optevolver/hyperparameter/__init__.py
optevolver/util/ExcelUtils.py
optevolver/util/JsonUtils.py
optevolver/util/__init__.py
optevolver-0.1.4.dist-info/LICENSE
optevolver-0.1.4.dist-info/METADATA
optevolver-0.1.4.dist-info/WHEEL
optevolver-0.1.4.dist-info/top_level.txt
optevolver-0.1.4.dist-info/RECORD
